nfp/__init__.py
nfp/_version.py
nfp/frameworks.py
nfp/layers/__init__.py
nfp/layers/graph_layers.py
nfp/layers/layers.py
nfp/models/__init__.py
nfp/models/losses.py
nfp/preprocessing/__init__.py
nfp/preprocessing/crystal_preprocessor.py
nfp/preprocessing/features.py
nfp/preprocessing/mol_preprocessor.py
nfp/preprocessing/preprocessor.py
nfp/preprocessing/tfrecord.py
nfp/preprocessing/tokenizer.py
nfp/preprocessing/xtb_preprocessor.py
nfp-0.3.12.dist-info/LICENSE
nfp-0.3.12.dist-info/METADATA
nfp-0.3.12.dist-info/WHEEL
nfp-0.3.12.dist-info/top_level.txt
nfp-0.3.12.dist-info/RECORD
