Metadata-Version: 2.1
Name: nfp
Version: 0.3.12
Summary: Keras layers for machine learning on graph structures
Home-page: https://github.com/NREL/nfp
Author: Peter St. John
Author-email: peter.stjohn@nrel.gov
License: UNKNOWN
Project-URL: Source, https://github.com/NREL/nfp
Platform: UNKNOWN
Classifier: Development Status :: 3 - Alpha
Classifier: Intended Audience :: Developers
Classifier: License :: OSI Approved :: MIT License
Classifier: Programming Language :: Python :: 3
Classifier: Programming Language :: Python :: 3.6
Classifier: Programming Language :: Python :: 3.7
Classifier: Programming Language :: Python :: 3.8
Classifier: Programming Language :: Python :: 3.9
License-File: LICENSE
Requires-Dist: numpy
Requires-Dist: tqdm
Requires-Dist: networkx (>2.0)
Provides-Extra: pymatgen
Requires-Dist: pymatgen ; extra == 'pymatgen'
Provides-Extra: rdkit
Requires-Dist: rdkit-pypi ; extra == 'rdkit'
Provides-Extra: test
Requires-Dist: pytest ; extra == 'test'
Provides-Extra: tf
Requires-Dist: tensorflow (>=2.4) ; extra == 'tf'
